supporttracker
